SimpleROT/ROT.py
SimpleROT/ROT_File.py
SimpleROT/__init__.py
SimpleROT-0.1.dist-info/METADATA
SimpleROT-0.1.dist-info/WHEEL
SimpleROT-0.1.dist-info/top_level.txt
SimpleROT-0.1.dist-info/RECORD
