Metadata-Version: 2.1
Name: SimpleROT
Version: 0.1
Summary: A basic library made with Python, useful for encrypting strings or files with ROT cipher.
Home-page: https://github.com/Fix-22/SimpleROT
Author: Fix-22
License: MIT
Platform: UNKNOWN
Classifier: Intended Audience :: Developers
Classifier: Programming Language :: Python
Classifier: Programming Language :: Python :: 3.10
Classifier: Operating System :: OS Independent
